ANBUtils/DBWorker.py
ANBUtils/__init__.py
ANBUtils/a.py
ANBUtils/db_tools.py
ANBUtils/easy_pickle.py
ANBUtils/environ.py
ANBUtils/id_work.py
ANBUtils/messenger.py
ANBUtils/tbox.py
ANBUtils-1.7.8.dist-info/METADATA
ANBUtils-1.7.8.dist-info/WHEEL
ANBUtils-1.7.8.dist-info/top_level.txt
ANBUtils-1.7.8.dist-info/RECORD
