Metadata-Version: 2.1
Name: ANBUtils
Version: 1.7.8
Summary: ANBUilts is a versatile Python package that offers a comprehensive set of utility functions and tools for data analysis, database operations, and messaging integration.
Home-page: https://github.com/redbson/ANBUtils
Author: Yafei Hou
Author-email: redbson@gmail.com
Requires-Python: >=3.11
Requires-Dist: matplotlib (>=3.0.0)
Requires-Dist: numpy (>=1.0.0)
Requires-Dist: pandas (>=1.0.0)
Requires-Dist: pymongo (>=4.0.2)
Requires-Dist: requests (>=2.0.0)
Requires-Dist: psutil (>=5.0.0)
